PY_TELUGU_VERSION/__init__.py
PY_TELUGU_VERSION/auto_update.py
PY_TELUGU_VERSION/keywords_te.json
PY_TELUGU_VERSION/main.py
PY_TELUGU_VERSION-1.2.dist-info/METADATA
PY_TELUGU_VERSION-1.2.dist-info/WHEEL
PY_TELUGU_VERSION-1.2.dist-info/entry_points.txt
PY_TELUGU_VERSION-1.2.dist-info/top_level.txt
PY_TELUGU_VERSION-1.2.dist-info/RECORD
