Metadata-Version: 2.1
Name: PY-TELUGU-VERSION
Version: 1.2
Summary: Literal Telugu package for Python programming
Author: sunstromium
Classifier: Programming Language :: Python :: 3
Classifier: Operating System :: OS Independent
Requires-Python: >=3.6
